iscacheable/__init__.py
iscacheable/__version__.py
iscacheable/cli.py
iscacheable-0.1.1.dist-info/METADATA
iscacheable-0.1.1.dist-info/RECORD
iscacheable-0.1.1.dist-info/WHEEL
iscacheable-0.1.1.dist-info/entry_points.txt
iscacheable-0.1.1.dist-info/top_level.txt
