Metadata-Version: 2.1
Name: iscacheable
Version: 0.1.1
Summary: A simple tool to determine if a URL is cacheable or not.
Home-page: https://github.com/gruns/iscacheable
Author: Ansgar Grunseid
Author-email: grunseid@gmail.com
License: MIT
Platform: any
Classifier: License :: OSI Approved :: MIT License
Classifier: Natural Language :: English
Classifier: Intended Audience :: Developers
Classifier: Topic :: Software Development :: Libraries
Classifier: Programming Language :: Python
Classifier: Programming Language :: Python :: 2
Classifier: Programming Language :: Python :: 2.7
Classifier: Programming Language :: Python :: 3
Classifier: Programming Language :: Python :: 3.4
Classifier: Programming Language :: Python :: 3.5
Classifier: Programming Language :: Python :: 3.6
Classifier: Programming Language :: Python :: 3.7
Classifier: Programming Language :: Python :: Implementation :: PyPy
Classifier: Programming Language :: Python :: Implementation :: CPython
Requires-Dist: cachecontrol
Requires-Dist: docopt (>=0.6.2)
Requires-Dist: requests
